langroid_pydantic_v2/__init__.py
langroid_pydantic_v2-0.1.0.dist-info/METADATA
langroid_pydantic_v2-0.1.0.dist-info/WHEEL
langroid_pydantic_v2-0.1.0.dist-info/RECORD
